projorg/__init__.py
projorg/config.py
projorg/experiment_logger.py
projorg/hyperparam_utils.py
projorg/project_path.py
projorg/setup_experiment.py
projorg/upload_to_cloud.py
projorg-1.1.dist-info/licenses/LICENSE
projorg-1.1.dist-info/METADATA
projorg-1.1.dist-info/WHEEL
projorg-1.1.dist-info/top_level.txt
projorg-1.1.dist-info/RECORD
