Metadata-Version: 2.4
Name: projorg
Version: 1.1
Summary: projorg: Python project organization and management
Home-page: https://github.com/alisiahkoohi/projorg
Author: Ali Siahkoohi
Author-email: alisk@rice.edu
Classifier: Programming Language :: Python :: 3
Classifier: License :: OSI Approved :: MIT License
Classifier: Operating System :: OS Independent
License-File: LICENSE
Requires-Dist: tqdm
Requires-Dist: h5py
Requires-Dist: gitpython
Requires-Dist: matplotlib
Dynamic: license-file
